pytest_codecarbon.py
pytest_codecarbon-1.0.0.dist-info/LICENSE
pytest_codecarbon-1.0.0.dist-info/METADATA
pytest_codecarbon-1.0.0.dist-info/WHEEL
pytest_codecarbon-1.0.0.dist-info/entry_points.txt
pytest_codecarbon-1.0.0.dist-info/top_level.txt
pytest_codecarbon-1.0.0.dist-info/RECORD
