Metadata-Version: 2.1
Name: pytest-codecarbon
Version: 1.0.0
Summary: Pytest plugin for measuring carbon emissions
Home-page: https://github.com/alexhroom/pytest-codecarbon
Author: Alex H. Room
Author-email: alex.room@btinternet.com
Project-URL: Bug Tracker, https://github.com/alexhroom/pytest-codecarbon/issues
Classifier: Programming Language :: Python :: 3
Classifier: License :: OSI Approved :: MIT License
Classifier: Operating System :: OS Independent
Classifier: Framework :: Pytest
Requires-Python: >3.6
License-File: LICENSE
Requires-Dist: pytest
Requires-Dist: codecarbon
Requires-Dist: pandas
